rpass/__init__.py
rpass/__main__.py
rpass/utils/__init__.py
rpass/utils/create_password.py
rpass-0.0.2.dist-info/LICENSE
rpass-0.0.2.dist-info/METADATA
rpass-0.0.2.dist-info/WHEEL
rpass-0.0.2.dist-info/entry_points.txt
rpass-0.0.2.dist-info/top_level.txt
rpass-0.0.2.dist-info/RECORD
