Metadata-Version: 2.1
Name: rpass
Version: 0.0.2
Summary: A simple commandline app for generating strong random passwords
Home-page: https://github.com/surajkarki66/rpass
Author: Suraj Karki
Author-email: suraj.karki500@protonmail.com
License: MIT
Keywords: rpass,generate,passlist
Platform: UNKNOWN
Classifier: Development Status :: 5 - Production/Stable
Classifier: Programming Language :: Python :: 2.7
Classifier: Programming Language :: Python :: 3
Classifier: Environment :: Console
Classifier: Intended Audience :: End Users/Desktop
Classifier: Intended Audience :: Developers
Classifier: License :: OSI Approved :: MIT License
Classifier: Natural Language :: English
Classifier: Topic :: Utilities
License-File: LICENSE
Requires-Dist: click (==8.0.1)
Requires-Dist: configobj (==5.0.6)
Requires-Dist: future (==0.18.2)
Requires-Dist: pyasn1 (==0.4.8)
Requires-Dist: pyasn1-modules (==0.2.8)
Requires-Dist: pyperclip (==1.8.2)
Requires-Dist: python-gnupg (==0.4.7)
Requires-Dist: python-ldap (==3.3.1)
Requires-Dist: secrets (==1.0.2)
Requires-Dist: six (==1.16.0)
Requires-Dist: systematic (==4.8.7)
Requires-Dist: uuid (==1.30)
